{
  "handlers": [
    {
      "name": "Corp Lookup",
      "type": "lookup",
      "screen_id": "markdown2",
      "title": "Kurum Bilgileri f",
      "actions": [
        {
          "name": "show_window",
          "requires_confirmation": false,
          "key": "_formatted_output"
        },
        {
          "name": "show_native_notification",
          "requires_confirmation": false,
          "key": "_formatted_output"
        },
        {
          "name": "copytoclipboard",
          "requires_confirmation": false,
          "key": "oid",
          "conditions": {
            "operator": "and",
            "conditions": [
              {
                "operator": "equals",
                "field": "_selector_key",
                "value": "drivercode"
              }
            ]
          }
        },
        {
          "name": "copytoclipboard",
          "requires_confirmation": false,
          "key": "drivercode",
          "conditions": {
            "operator": "and",
            "conditions": [
              {
                "operator": "equals",
                "field": "_selector_key",
                "value": "oid"
              }
            ]
          }
        }
      ],
      "path": "C:\\Finder\\corp_data.txt",
      "delimiter": "||",
      "key_names": [
        "drivercode",
        "oid"
      ],
      "value_names": [
        "drivercode",
        "oid",
        "name",
        "engine"
      ],
      "output_format": "$file:C:\\Finder\\output_template\\markdown_capabilities.txt",
      "user_inputs": [
        {
          "key": "platform",
          "title": "Platform Selection",
          "message": "Please select your target platform:",
          "is_required": true,
          "is_selection_list": true,
          "is_password": false,
          "selection_items": [
            {
              "value": "windows",
              "display": "Windows"
            },
            {
              "value": "linux",
              "display": "Linux"
            },
            {
              "value": "macos",
              "display": "macOS"
            }
          ],
          "is_multi_select": false,
          "is_file_picker": false,
          "is_folder_picker": false,
          "is_multi_line": false,
          "is_date": false,
          "is_date_picker": false,
          "is_time": false,
          "is_time_picker": false,
          "is_date_time": false,
          "is_datetime_picker": false,
          "default_value": "windows"
        },
        {
          "key": "api_key",
          "title": "API Key",
          "message": "Enter your API key:",
          "validation_regex": "^[A-Za-z0-9-_]{3}$",
          "is_required": true,
          "is_selection_list": false,
          "is_password": true,
          "is_multi_select": false,
          "is_file_picker": false,
          "is_folder_picker": false,
          "is_multi_line": false,
          "is_date": false,
          "is_date_picker": false,
          "is_time": false,
          "is_time_picker": false,
          "is_date_time": false,
          "is_datetime_picker": false,
          "default_value": ""
        },
        {
          "key": "email",
          "title": "Email Address",
          "message": "Enter your email address:",
          "validation_regex": "^[a-zA-Z0-9._%+-]+@[a-zA-Z0-9.-]+\\.[a-zA-Z]{2,}$",
          "is_required": true,
          "is_selection_list": false,
          "is_password": false,
          "is_multi_select": false,
          "is_file_picker": false,
          "is_folder_picker": false,
          "is_multi_line": false,
          "is_date": false,
          "is_date_picker": false,
          "is_time": false,
          "is_time_picker": false,
          "is_date_time": false,
          "is_datetime_picker": false,
          "default_value": "user@example.com"
        }
      ],
      "requires_confirmation": false,
      "url": "",
      "cron_enabled": true,
      "auto_focus_tab": false,
      "bring_window_to_front": false,
      "enabled": true,
      "mcp_enabled": false,
      "mcp_headless": false,
      "mcp_seed_overwrite": false
    },
    {
      "name": "Json formatter wpf",
      "type": "custom",
      "screen_id": "jsonformatter",
      "validator": "jsonvalidator",
      "context_provider": "jsonvalidator",
      "title": "JSON Formatter",
      "actions": [
        {
          "name": "show_window",
          "requires_confirmation": false,
          "key": "_input"
        }
      ],
      "requires_confirmation": false,
      "url": "",
      "cron_enabled": true,
      "auto_focus_tab": false,
      "bring_window_to_front": false,
      "enabled": true,
      "mcp_enabled": false,
      "mcp_headless": false,
      "mcp_seed_overwrite": false
    },
    {
      "name": "Xml formatter wpf",
      "type": "custom",
      "screen_id": "xmlformatter",
      "validator": "xmlvalidator",
      "context_provider": "xmlvalidator",
      "title": "XML Formatter",
      "actions": [
        {
          "name": "show_window",
          "requires_confirmation": false,
          "key": "_input"
        }
      ],
      "requires_confirmation": false,
      "url": "",
      "cron_enabled": true,
      "auto_focus_tab": false,
      "bring_window_to_front": false,
      "enabled": true,
      "mcp_enabled": false,
      "mcp_headless": false,
      "mcp_seed_overwrite": false
    },
    {
      "name": "Customer Lookup",
      "type": "lookup",
      "screen_id": "markdown2",
      "title": "Müşteri Bilgileri",
      "actions": [
        {
          "name": "show_window",
          "requires_confirmation": false,
          "key": "_formatted_output"
        }
      ],
      "path": "C:\\Finder\\customer_data.txt",
      "delimiter": "||",
      "key_names": [
        "customer_id",
        "email"
      ],
      "value_names": [
        "customer_id",
        "name",
        "email",
        "phone"
      ],
      "seeder": {
        "path": "C:\\$(customer_id).txt",
        "user_input": "hello world",
        "api_url": "https://api.example.com",
        "delegate_cust_id": "T67526",
        "customer_id_cloned": "$(customer_id)",
        "env_t": "$(env)",
        "url_param": "$func:base64encode($(name))",
        "url_param_encode": "$func:url.encode($(url_param))",
        "real_url": "www.google.com/p=$(url_param_encode)&env=$(env_t)",
        "encoded_pipeline": "$func:{{ $(pipeline) | string.trim | string.upper }}"
      },
      "constant_seeder": {
        "pipeline": "        hello|world     ",
        "env": "1",
        "input_text": "  Hello World  ",
        "dirty_text": "  Some Dirty Text With Spaces  ",
        "full_name": "  Murat AY  ",
        "sentence": "The quick brown fox jumps over the lazy dog",
        "camel_case": "thisIsCamelCase",
        "lower_text": "this is lower text",
        "text_input": "word1 word2 word3",
        "base_url": "https://api.example.com",
        "search_base": "https://search.example.com",
        "user_id": "12345",
        "search_term": "hello world",
        "full_url": "https://www.example.com/path/to/resource",
        "file_url": "https://cdn.example.com/files/document.pdf",
        "url_input": "  HTTPS://WWW.EXAMPLE.COM/PATH  ",
        "user_json": "{\"user\":{\"profile\":{\"name\":\"john doe\",\"email\":\"john@example.com\"}}}",
        "data_json": "{\"message\":\"profile ..%%\"}",
        "items_json": "{\"items\":[{\"name\":\"item1\"},{\"name\":\"item2\"}]}",
        "collection_json": "{\"data\":[1,2,3,4,5]}",
        "api_response": "{\"result\":{\"user\":{\"email\":\"  USER@EXAMPLE.COM  \"}}}",
        "nested_json": "{\"users\":[{\"profile\":{\"settings\":{\"theme\":\"DARK MODE\"}}}]",
        "number1": "15",
        "decimal_number": "3.14159",
        "base_number": "10",
        "zero_value": "0",
        "array_json": "[\"first\",\"second\",\"third\"]",
        "items_array": "[\"item1\",\"item2\",\"item3\"]",
        "tags_array": "[\"tag_web\",\"tag_api\",\"tag_json\"]",
        "small_array": "[\"a\",\"b\"]",
        "api_endpoint": "https://httpbin.org/json",
        "base_api": "https://api.github.com",
        "password": "  MySecretPassword  ",
        "sensitive_data": "confidential information",
        "input_data": "user input data",
        "user_input": "  User Input With Spaces  ",
        "raw_token": "abc-def-ghi-jkl",
        "file_path": "C:\\\\Users\\\\Documents\\\\MyFile.txt",
        "file_name": "document.PDF",
        "raw_filename": "My File Name İçerik.txt",
        "raw_username": "  Murat AY  ",
        "email_input": "  USER@EXAMPLE.COM  ",
        "phone_number": "(555) 123-4567",
        "unix_timestamp": "1640995200",
        "invalid_json": "{\"invalid\": json}",
        "maybe_null": ""
      },
      "user_inputs": [],
      "file_extensions": [
        ".jpg",
        ".png",
        ".gif"
      ],
      "requires_confirmation": false,
      "url": "",
      "cron_enabled": true,
      "auto_focus_tab": true,
      "bring_window_to_front": true,
      "enabled": true,
      "mcp_enabled": false,
      "mcp_headless": false,
      "mcp_seed_overwrite": false
    },
    {
      "name": "Strategy Query auto focus bringto",
      "description": "[NorthPole].[Strategy].[Parameter] tablosundan [Name] kolonundan bilgileri getirir.",
      "type": "database",
      "screen_id": "markdown2",
      "title": "Strategy Bilgileri auto focus bringto",
      "regex": "^\\S+$",
      "connectionString": "Server=localhost\\SQLEXPRESS;Database=$config:database.sql_db;Trusted_Connection=$config:database.trusted_con;TrustServerCertificate=$config:database.trusted_cert;",
      "query": "SELECT [ParameterId],[Name],[Description],[DefaultValue],[IsArray],[Seperator],[FormatedName] FROM [Strategy].[Parameter] WHERE Name = @p_input",
      "connector": "mssql",
      "actions": [
        {
          "name": "show_window",
          "requires_confirmation": false,
          "key": "_formatted_output",
          "conditions": {
            "operator": "and",
            "conditions": [
              {
                "operator": "greater_than",
                "field": "_count",
                "value": "0"
              },
              {
                "operator": "not_equals",
                "field": "_trigger",
                "value": "mcp"
              }
            ]
          }
        }
      ],
      "output_format": "$file:C:\\Finder\\output_template\\single_row.txt",
      "requires_confirmation": false,
      "url": "",
      "cron_enabled": true,
      "auto_focus_tab": true,
      "bring_window_to_front": true,
      "enabled": true,
      "mcp_enabled": true,
      "mcp_tool_name": "strategy_query",
      "mcp_description": "Strategy Parameter bilgisini Name ile getirir.",
      "mcp_input_schema": {
        "type": "object",
        "properties": {
          "name": {
            "type": "string"
          }
        },
        "required": [
          "name"
        ]
      },
      "mcp_input_template": "$(name)",
      "mcp_return_keys": [
        "_formatted_output"
      ],
      "mcp_headless": false,
      "mcp_seed_overwrite": false
    },
    {
      "name": "Strategy Query1",
      "description": "[NorthPole].[Strategy].[Parameter] tablosundan [Name] kolonundan bilgileri getirir.",
      "type": "database",
      "screen_id": "markdown2",
      "title": "Strategy Bilgileri1",
      "regex": "^\\S+$",
      "connectionString": "Server=localhost\\SQLEXPRESS;Database=$config:database.sql_db;Trusted_Connection=$config:database.trusted_con;TrustServerCertificate=$config:database.trusted_cert;",
      "query": "SELECT [ParameterId],[Name],[Description],[DefaultValue],[IsArray],[Seperator],[FormatedName] FROM [Strategy].[Parameter] WHERE Name = @p_input",
      "connector": "mssql",
      "actions": [
        {
          "name": "show_window",
          "requires_confirmation": false,
          "key": "_formatted_output",
          "conditions": {
            "operator": "and",
            "conditions": [
              {
                "operator": "greater_than",
                "field": "_count",
                "value": "0"
              }
            ]
          }
        }
      ],
      "output_format": "$file:C:\\Finder\\output_template\\single_row.txt",
      "requires_confirmation": false,
      "url": "",
      "cron_enabled": true,
      "auto_focus_tab": false,
      "bring_window_to_front": false,
      "enabled": false,
      "mcp_enabled": false,
      "mcp_headless": false,
      "mcp_seed_overwrite": false
    },
    {
      "name": "Strategy Query2",
      "description": "[NorthPole].[Strategy].[Parameter] tablosundan [Name] kolonundan bilgileri getirir.",
      "type": "database",
      "screen_id": "markdown2",
      "title": "Strategy Bilgileri2",
      "regex": "^\\S+$",
      "connectionString": "Server=localhost\\SQLEXPRESS;Database=$config:database.sql_db;Trusted_Connection=$config:database.trusted_con;TrustServerCertificate=$config:database.trusted_cert;",
      "query": "SELECT [ParameterId],[Name],[Description],[DefaultValue],[IsArray],[Seperator],[FormatedName] FROM [Strategy].[Parameter] WHERE Name = @p_input",
      "connector": "mssql",
      "actions": [
        {
          "name": "show_window",
          "requires_confirmation": false,
          "key": "_formatted_output",
          "conditions": {
            "operator": "and",
            "conditions": [
              {
                "operator": "greater_than",
                "field": "_count",
                "value": "0"
              }
            ]
          }
        }
      ],
      "requires_confirmation": false,
      "url": "",
      "cron_enabled": true,
      "auto_focus_tab": true,
      "bring_window_to_front": true,
      "enabled": false,
      "mcp_enabled": true,
      "mcp_headless": false,
      "mcp_seed_overwrite": false
    },
    {
      "name": "Open File",
      "type": "file",
      "actions": [
        {
          "name": "open_file",
          "requires_confirmation": false
        },
        {
          "name": "print_details",
          "requires_confirmation": false
        }
      ],
      "file_extensions": [
        ".html",
        ".css"
      ],
      "requires_confirmation": false,
      "url": "",
      "cron_enabled": true,
      "auto_focus_tab": false,
      "bring_window_to_front": false,
      "enabled": false,
      "mcp_enabled": false,
      "mcp_headless": false,
      "mcp_seed_overwrite": false
    },
    {
      "name": "LGX Detail Query",
      "type": "regex",
      "regex": "(\\d+)\\t(\\d+)\\t(\\d{8})",
      "groups": [
        "oid",
        "trxid",
        "processdate"
      ],
      "actions": [
        {
          "name": "print_details",
          "requires_confirmation": false
        }
      ],
      "output_format": "Select * from lgx.log_dtl where OID = $(oid) and trxid=$(trxid) and processdate = $(processdate)",
      "requires_confirmation": false,
      "url": "",
      "cron_enabled": true,
      "auto_focus_tab": false,
      "bring_window_to_front": false,
      "enabled": false,
      "mcp_enabled": false,
      "mcp_headless": false,
      "mcp_seed_overwrite": false
    },
    {
      "name": "Hello",
      "type": "regex",
      "screen_id": "markdown2",
      "title": "First handler",
      "regex": "\\b\\w{3,}\\b",
      "actions": [
        {
          "name": "show_window",
          "requires_confirmation": false,
          "key": "_formatted_output"
        }
      ],
      "output_format": "\uD83D\uDC4B Hello $(_match)<br>Welcome!!",
      "requires_confirmation": false,
      "url": "",
      "cron_enabled": true,
      "auto_focus_tab": true,
      "bring_window_to_front": true,
      "enabled": false,
      "mcp_enabled": false,
      "mcp_headless": false,
      "mcp_seed_overwrite": false
    },
    {
      "name": "Özel DB Handler",
      "type": "custom",
      "connectionString": "Server=localhost\\SQLEXPRESS;Database=123;Connection Timeout=30;Trusted_Connection=True;",
      "query": "SELECT * FROM 123.dbo.Users",
      "requires_confirmation": false,
      "url": "",
      "cron_enabled": true,
      "auto_focus_tab": false,
      "bring_window_to_front": false,
      "enabled": true,
      "mcp_enabled": false,
      "mcp_headless": false,
      "mcp_seed_overwrite": false
    },
    {
      "name": "Stack Trace Analysis",
      "type": "regex",
      "regex": "at (\\S+)\\((\\S+\\.java):(\\d+)\\)",
      "groups": [
        "class_name",
        "file_name",
        "line_number"
      ],
      "actions": [
        {
          "name": "print_details",
          "requires_confirmation": false
        }
      ],
      "requires_confirmation": false,
      "url": "",
      "cron_enabled": true,
      "auto_focus_tab": false,
      "bring_window_to_front": false,
      "enabled": true,
      "mcp_enabled": false,
      "mcp_headless": false,
      "mcp_seed_overwrite": false
    },
    {
      "name": "Transaction Viewer - IBTools",
      "type": "regex",
      "screen_id": "url_viewer",
      "title": "Transaction Viewer - IBTools",
      "regex": "^\\d{16}$",
      "groups": [
        "trxid"
      ],
      "actions": [
        {
          "name": "show_window",
          "requires_confirmation": false,
          "key": "url"
        }
      ],
      "seeder": {
        "environmentId": "1",
        "shared_webview_profile": "D:\\Contextualizer\\sharedviewprofile",
        "url": "https://ibtools-opensol-dev-smggeneric.apps.ocptstinf01.finansbank.com.tr/transactionview?trxid=$(trxid)&environmentId=$(environmentId)"
      },
      "requires_confirmation": true,
      "url": "",
      "cron_enabled": true,
      "auto_focus_tab": false,
      "bring_window_to_front": false,
      "enabled": true,
      "mcp_enabled": false,
      "mcp_headless": false,
      "mcp_seed_overwrite": false
    },
    {
      "name": "Sample Lookup",
      "type": "lookup",
      "screen_id": "markdown2",
      "title": "Sample Lookup Handler",
      "actions": [
        {
          "name": "show_window",
          "requires_confirmation": false,
          "key": "_formatted_output"
        }
      ],
      "path": "c:\\Users\\murat\\source\\repos\\tool-test\\sample_lookup_data.txt",
      "delimiter": "||",
      "key_names": [
        "drivercode"
      ],
      "value_names": [
        "drivercode",
        "oid",
        "name",
        "engine"
      ],
      "output_format": "Driver: $(drivercode), Name: $(name), Engine: $(engine)",
      "requires_confirmation": false,
      "url": "",
      "cron_enabled": true,
      "auto_focus_tab": false,
      "bring_window_to_front": false,
      "enabled": true,
      "mcp_enabled": false,
      "mcp_headless": false,
      "mcp_seed_overwrite": false
    },
    {
      "name": "GitHub User Info Sentetik",
      "description": "GitHub kullanıcı bilgilerini getirir",
      "type": "Synthetic",
      "screen_id": "markdown2",
      "title": "Github User Info",
      "regex": "^[a-zA-Z0-9-]+$",
      "groups": [
        "username"
      ],
      "actions": [
        {
          "name": "copytoclipboard",
          "requires_confirmation": false,
          "key": "_self"
        },
        {
          "name": "show_window",
          "requires_confirmation": false,
          "key": "_formatted_output"
        }
      ],
      "output_format": "GitHub User: $(name)\nFollowers: $(followers)\nFollowing: $(following)",
      "requires_confirmation": true,
      "url": "https://api.github.com/users/$(_input)",
      "method": "GET",
      "headers": {
        "Accept": "application/vnd.github.v3+json",
        "User-Agent": "Contextualizer"
      },
      "actual_type": "api",
      "synthetic_input": {
        "key": "drivercode",
        "title": "Kullanıcı adi gir",
        "message": "Kullanıcı Adı:",
        "is_required": true,
        "is_selection_list": false,
        "is_password": false,
        "is_multi_select": false,
        "is_file_picker": false,
        "is_folder_picker": false,
        "is_multi_line": false,
        "is_date": false,
        "is_date_picker": false,
        "is_time": false,
        "is_time_picker": false,
        "is_date_time": false,
        "is_datetime_picker": false,
        "default_value": ""
      },
      "cron_enabled": true,
      "auto_focus_tab": false,
      "bring_window_to_front": false,
      "enabled": true,
      "mcp_enabled": false,
      "mcp_headless": false,
      "mcp_seed_overwrite": false
    },
    {
      "name": "API Health Monitor",
      "description": "Fetches API data every minute",
      "type": "cron",
      "screen_id": "jsonformatter",
      "title": "1 Minute API Monitor",
      "actions": [
        {
          "name": "show_window",
          "requires_confirmation": false,
          "key": "RawResponse"
        }
      ],
      "output_format": "API Response at $(execution_time): $(slideshow.title)",
      "requires_confirmation": false,
      "url": "$config:endpoints.cron_example_url",
      "method": "GET",
      "headers": {
        "Accept": "application/json",
        "User-Agent": "Contextualizer-Monitor"
      },
      "actual_type": "api",
      "cron_job_id": "api_health_1min",
      "cron_expression": "0 0/1 * * * ? *",
      "cron_enabled": true,
      "auto_focus_tab": false,
      "bring_window_to_front": false,
      "enabled": false,
      "mcp_enabled": false,
      "mcp_headless": false,
      "mcp_seed_overwrite": false
    },
    {
      "name": "Documentation",
      "type": "manual",
      "screen_id": "url_viewer",
      "title": "Documentation",
      "actions": [
        {
          "name": "show_window",
          "requires_confirmation": false,
          "key": "url"
        }
      ],
      "constant_seeder": {
        "url": "file:///C:/Users/murat/source/repos/Contextualizer/docs/index.html"
      },
      "requires_confirmation": false,
      "url": "",
      "cron_enabled": true,
      "auto_focus_tab": false,
      "bring_window_to_front": false,
      "enabled": false,
      "mcp_enabled": false,
      "mcp_headless": false,
      "mcp_seed_overwrite": false
    },
    {
      "name": "Branch Viewer",
      "type": "manual",
      "screen_id": "url_viewer",
      "title": "Branch Viewer Enpara",
      "actions": [
        {
          "name": "show_window",
          "requires_confirmation": false,
          "key": "url"
        }
      ],
      "seeder": {
        "shared_webview_profile": "C:\\Finder\\sharedviewprofile",
        "url": "http://github.com/murat7Ay/"
      },
      "user_inputs": [
        {
          "key": "organizationName",
          "title": "Organization Selection",
          "message": "Please select Organization:",
          "is_required": true,
          "is_selection_list": true,
          "is_password": false,
          "selection_items": [
            {
              "value": "CoreFinans",
              "display": "Core Finans"
            },
            {
              "value": "Enpara",
              "display": "Enpara"
            }
          ],
          "is_multi_select": false,
          "is_file_picker": false,
          "is_folder_picker": false,
          "is_multi_line": false,
          "is_date": false,
          "is_date_picker": false,
          "is_time": false,
          "is_time_picker": false,
          "is_date_time": false,
          "is_datetime_picker": false,
          "default_value": "CoreFinans"
        },
        {
          "key": "projectName",
          "title": "Project Selection",
          "message": "Please select project name:",
          "is_required": true,
          "is_selection_list": true,
          "is_password": false,
          "selection_items": [
            {
              "value": "CashManagementPayments",
              "display": "Cash Management Payments"
            },
            {
              "value": "CashManagement",
              "display": "Cash Management"
            },
            {
              "value": "Open Banking",
              "display": "OpenBanking"
            }
          ],
          "is_multi_select": false,
          "is_file_picker": false,
          "is_folder_picker": false,
          "is_multi_line": false,
          "is_date": false,
          "is_date_picker": false,
          "is_time": false,
          "is_time_picker": false,
          "is_date_time": false,
          "is_datetime_picker": false,
          "default_value": "CashManagement",
          "dependent_key": "organizationName",
          "dependent_selection_item_map": {
            "Enpara": {
              "selection_items": [
                {
                  "value": "CashManagementPayments",
                  "display": "Cash Management Payments"
                }
              ],
              "default_value": "CashManagementPayments"
            },
            "CoreFinans": {
              "selection_items": [
                {
                  "value": "CashManagementPayments",
                  "display": "Cash Management Payments"
                },
                {
                  "value": "CashManagement",
                  "display": "Cash Management"
                },
                {
                  "value": "Open Banking",
                  "display": "OpenBanking"
                }
              ],
              "default_value": "CashManagement"
            }
          }
        }
      ],
      "requires_confirmation": false,
      "url": "",
      "cron_enabled": true,
      "auto_focus_tab": false,
      "bring_window_to_front": false,
      "enabled": true,
      "mcp_enabled": false,
      "mcp_headless": false,
      "mcp_seed_overwrite": false
    },
    {
      "name": "StandartType2 DBS Projesi oluştur",
      "type": "manual",
      "screen_id": "markdown2",
      "title": "DBS Projesi",
      "actions": [
        {
          "name": "show_window",
          "requires_confirmation": false,
          "key": "_self"
        }
      ],
      "user_inputs": [
        {
          "key": "drivercode",
          "title": "Kurum kodunu gir",
          "message": "Kurum kodu:",
          "is_required": true,
          "is_selection_list": false,
          "is_password": false,
          "is_multi_select": false,
          "is_file_picker": false,
          "is_folder_picker": false,
          "is_multi_line": true,
          "is_date": false,
          "is_date_picker": false,
          "is_time": false,
          "is_time_picker": false,
          "is_date_time": false,
          "is_datetime_picker": false,
          "default_value": ""
        },
        {
          "key": "packagename",
          "title": "Paket ismini gir",
          "message": "Paket ismi:",
          "is_required": true,
          "is_selection_list": false,
          "is_password": false,
          "is_multi_select": false,
          "is_file_picker": false,
          "is_folder_picker": false,
          "is_multi_line": false,
          "is_date": false,
          "is_date_picker": false,
          "is_time": false,
          "is_time_picker": false,
          "is_date_time": false,
          "is_datetime_picker": false,
          "default_value": ""
        },
        {
          "key": "platform_multi_select",
          "title": "Platform Selection",
          "message": "Please select your target platform:",
          "is_required": true,
          "is_selection_list": true,
          "is_password": false,
          "selection_items": [
            {
              "value": "windows",
              "display": "Windows"
            },
            {
              "value": "linux",
              "display": "Linux"
            },
            {
              "value": "macos",
              "display": "macOS"
            }
          ],
          "is_multi_select": true,
          "is_file_picker": false,
          "is_folder_picker": false,
          "is_multi_line": false,
          "is_date": false,
          "is_date_picker": false,
          "is_time": false,
          "is_time_picker": false,
          "is_date_time": false,
          "is_datetime_picker": false,
          "default_value": "windows,linux"
        },
        {
          "key": "filepath",
          "title": "Paket ismini gir",
          "message": "Paket ismi:",
          "is_required": true,
          "is_selection_list": false,
          "is_password": false,
          "is_multi_select": false,
          "is_file_picker": true,
          "is_folder_picker": false,
          "is_multi_line": false,
          "is_date": false,
          "is_date_picker": false,
          "is_time": false,
          "is_time_picker": false,
          "is_date_time": false,
          "is_datetime_picker": false,
          "default_value": ""
        }
      ],
      "requires_confirmation": false,
      "url": "",
      "cron_enabled": true,
      "auto_focus_tab": false,
      "bring_window_to_front": false,
      "enabled": false,
      "mcp_enabled": false,
      "mcp_headless": false,
      "mcp_seed_overwrite": false
    },
    {
      "name": "Synthetic Strategy Query",
      "type": "synthetic",
      "title": "Interactive Strategy Query",
      "requires_confirmation": false,
      "url": "",
      "reference_handler": "Strategy Query",
      "synthetic_input": {
        "key": "drivercode",
        "title": "Kurum kodunu gir",
        "message": "Kurum kodu:",
        "is_required": true,
        "is_selection_list": false,
        "is_password": false,
        "is_multi_select": false,
        "is_file_picker": false,
        "is_folder_picker": false,
        "is_multi_line": true,
        "is_date": false,
        "is_date_picker": false,
        "is_time": false,
        "is_time_picker": false,
        "is_date_time": false,
        "is_datetime_picker": false,
        "default_value": ""
      },
      "cron_enabled": true,
      "auto_focus_tab": false,
      "bring_window_to_front": false,
      "enabled": false,
      "mcp_enabled": false,
      "mcp_headless": false,
      "mcp_seed_overwrite": false
    },
    {
      "name": "Merhaba",
      "type": "regex",
      "screen_id": "markdown2",
      "title": "İlk Handler",
      "regex": "\\b\\w{3,}\\b",
      "actions": [
        {
          "name": "show_window",
          "requires_confirmation": false,
          "key": "_formatted_output"
        }
      ],
      "output_format": "\uD83D\uDC4B Merhaba $func:{{$(_match) | string.upper}}<br>Hoş geldiniz!!",
      "requires_confirmation": false,
      "url": "",
      "cron_enabled": true,
      "auto_focus_tab": true,
      "bring_window_to_front": true,
      "enabled": true,
      "mcp_enabled": false,
      "mcp_headless": false,
      "mcp_seed_overwrite": false
    },
    {
      "name": "list_tables",
      "description": "List all tables in the database with their schema and table names",
      "type": "Database",
      "connectionString": "Server=localhost\\SQLEXPRESS;Database=$config:database.sql_db;Trusted_Connection=$config:database.trusted_con;TrustServerCertificate=$config:database.trusted_cert;",
      "query": "SELECT TABLE_SCHEMA AS schema_name, TABLE_NAME AS table_name, TABLE_TYPE AS table_type FROM INFORMATION_SCHEMA.TABLES WHERE TABLE_TYPE = 'BASE TABLE' ORDER BY TABLE_SCHEMA, TABLE_NAME",
      "connector": "mssql",
      "requires_confirmation": false,
      "url": "",
      "cron_enabled": true,
      "auto_focus_tab": false,
      "bring_window_to_front": false,
      "enabled": true,
      "mcp_enabled": true,
      "mcp_tool_name": "list_tables",
      "mcp_description": "List all tables in the MSSQL database with schema and table names",
      "mcp_headless": false,
      "mcp_seed_overwrite": false
    },
    {
      "name": "get_table",
      "description": "Get detailed information about a table including columns, data types, indexes, primary keys, and foreign keys. Requires table_name parameter and optional schema parameter (defaults to 'dbo').",
      "type": "Database",
      "connectionString": "Server=localhost\\SQLEXPRESS;Database=$config:database.sql_db;Trusted_Connection=$config:database.trusted_con;TrustServerCertificate=$config:database.trusted_cert;",
      "query": "SELECT \n    c.COLUMN_NAME AS column_name,\n    c.DATA_TYPE AS data_type,\n    c.CHARACTER_MAXIMUM_LENGTH AS max_length,\n    c.NUMERIC_PRECISION AS numeric_precision,\n    c.NUMERIC_SCALE AS numeric_scale,\n    c.IS_NULLABLE AS is_nullable,\n    c.COLUMN_DEFAULT AS column_default,\n    c.ORDINAL_POSITION AS ordinal_position,\n    CASE WHEN pk.COLUMN_NAME IS NOT NULL THEN 1 ELSE 0 END AS is_primary_key,\n    CASE WHEN fk.COLUMN_NAME IS NOT NULL THEN 1 ELSE 0 END AS is_foreign_key,\n    fk.REFERENCED_TABLE_SCHEMA AS referenced_schema,\n    fk.REFERENCED_TABLE_NAME AS referenced_table,\n    fk.REFERENCED_COLUMN_NAME AS referenced_column,\n    i.name AS index_name,\n    i.type_desc AS index_type,\n    ic.is_included_column AS is_included_in_index\nFROM INFORMATION_SCHEMA.COLUMNS c\nLEFT JOIN (\n    SELECT ku.TABLE_SCHEMA, ku.TABLE_NAME, ku.COLUMN_NAME\n    FROM INFORMATION_SCHEMA.TABLE_CONSTRAINTS tc\n    INNER JOIN INFORMATION_SCHEMA.KEY_COLUMN_USAGE ku\n        ON tc.CONSTRAINT_NAME = ku.CONSTRAINT_NAME\n        AND tc.TABLE_SCHEMA = ku.TABLE_SCHEMA\n        AND tc.TABLE_NAME = ku.TABLE_NAME\n    WHERE tc.CONSTRAINT_TYPE = 'PRIMARY KEY'\n) pk ON c.TABLE_SCHEMA = pk.TABLE_SCHEMA \n    AND c.TABLE_NAME = pk.TABLE_NAME \n    AND c.COLUMN_NAME = pk.COLUMN_NAME\nLEFT JOIN (\n    SELECT \n        kcu.TABLE_SCHEMA,\n        kcu.TABLE_NAME,\n        kcu.COLUMN_NAME,\n        ccu.TABLE_SCHEMA AS REFERENCED_TABLE_SCHEMA,\n        ccu.TABLE_NAME AS REFERENCED_TABLE_NAME,\n        ccu.COLUMN_NAME AS REFERENCED_COLUMN_NAME\n    FROM INFORMATION_SCHEMA.REFERENTIAL_CONSTRAINTS rc\n    INNER JOIN INFORMATION_SCHEMA.KEY_COLUMN_USAGE kcu\n        ON rc.CONSTRAINT_NAME = kcu.CONSTRAINT_NAME\n        AND rc.CONSTRAINT_SCHEMA = kcu.CONSTRAINT_SCHEMA\n    INNER JOIN INFORMATION_SCHEMA.KEY_COLUMN_USAGE ccu\n        ON rc.UNIQUE_CONSTRAINT_NAME = ccu.CONSTRAINT_NAME\n        AND rc.UNIQUE_CONSTRAINT_SCHEMA = ccu.CONSTRAINT_SCHEMA\n) fk ON c.TABLE_SCHEMA = fk.TABLE_SCHEMA \n    AND c.TABLE_NAME = fk.TABLE_NAME \n    AND c.COLUMN_NAME = fk.COLUMN_NAME\nLEFT JOIN sys.indexes i \n    ON i.object_id = OBJECT_ID(QUOTENAME(c.TABLE_SCHEMA) + '.' + QUOTENAME(c.TABLE_NAME))\nLEFT JOIN sys.index_columns ic \n    ON ic.object_id = i.object_id \n    AND ic.index_id = i.index_id\n    AND ic.column_id = COLUMNPROPERTY(OBJECT_ID(QUOTENAME(c.TABLE_SCHEMA) + '.' + QUOTENAME(c.TABLE_NAME)), c.COLUMN_NAME, 'ColumnID')\nWHERE c.TABLE_SCHEMA = COALESCE(@schema, 'dbo')\n    AND c.TABLE_NAME = @table_name\nORDER BY c.ORDINAL_POSITION, i.name, ic.key_ordinal",
      "connector": "mssql",
      "requires_confirmation": false,
      "url": "",
      "cron_enabled": true,
      "auto_focus_tab": false,
      "bring_window_to_front": false,
      "enabled": true,
      "mcp_enabled": true,
      "mcp_tool_name": "get_table",
      "mcp_description": "Get detailed table information including columns, data types, indexes, primary keys, and foreign keys. Parameters: @table_name (required), @schema (optional, defaults to 'dbo')",
      "mcp_headless": false,
      "mcp_seed_overwrite": false
    }
  ]
}