{
  "id": "branchapp-page-access",
  "name": "Branchapp Page Access",
  "version": "1.0.0",
  "author": "Murat",
  "description": "Core test ekranına yetkisi olan kullanıcıyı getirir",
  "tags": [
    "database",
    "oracle",
    "plsql",
    "authorization"
  ],
  "dependencies": [
    "simple_print_key"
  ],
  "handlerJson": {
    "name": "Branchapp Page Access",
    "requires_confirmation": false,
    "screen_id": "markdown2",
    "regex": "(NYT|URN|KRD)[0-9]{5}$",
    "title": "Ekrana yetkisi olan kullanıcı",
    "description": "Core test ekranına yetkisi olan kullanıcıyı getirir.",
    "type": "database",
    "connectionString": "$config:database.connection_string",
    "connector": "plsql",
    "query": "SELECT * FROM ( SELECT DISTINCT k.KULLANICIKODU , k.ORGANIZASYONKODU, k.BIRIMKODU, k.GISEYETKILISI, k.HESAPYETKILISI, k.UYGKODU, k.AYGKODU FROM URN.PLM_MENU_HAKLARI a, URN.ORG_KULLANICI_VW k WHERE a.menuoid IN ( SELECT oid FROM urn.org_menu WHERE status = 1 AND ekranadi = :p_input) AND k.kullanicikodu = a.KULLANICIKODU ORDER BY k.KULLANICIKODU ) WHERE ROWNUM <= 20",
    "actions": [
      {
        "name": "simple_print_key",
        "key": "_formatted_output"
      }
    ]
  },
  "metadata": {
    "category": "Database",
    "handlerType": "database",
    "database": "Oracle"
  }
}

